{
"meta":{"test_sets":[],"test_metrics":[],"learn_metrics":[{"best_value":"Min","name":"RMSE"}],"launch_mode":"Train","parameters":"","iteration_count":100,"learn_sets":["learn"],"name":"experiment"},
"iterations":[
{"learn":[13.96962521],"iteration":0,"passed_time":0.001801586572,"remaining_time":0.1783570706},
{"learn":[13.09082657],"iteration":1,"passed_time":0.003234863341,"remaining_time":0.1585083037},
{"learn":[12.27861651],"iteration":2,"passed_time":0.004634109908,"remaining_time":0.1498362204},
{"learn":[11.53029884],"iteration":3,"passed_time":0.006160328411,"remaining_time":0.1478478819},
{"learn":[10.87492512],"iteration":4,"passed_time":0.007784629252,"remaining_time":0.1479079558},
{"learn":[10.38155225],"iteration":5,"passed_time":0.00931583805,"remaining_time":0.1459481295},
{"learn":[9.857621344],"iteration":6,"passed_time":0.01075119912,"remaining_time":0.1428373597},
{"learn":[9.411181059],"iteration":7,"passed_time":0.0120302377,"remaining_time":0.1383477336},
{"learn":[8.998198398],"iteration":8,"passed_time":0.01297971643,"remaining_time":0.131239355},
{"learn":[8.588034504],"iteration":9,"passed_time":0.01389127692,"remaining_time":0.1250214923},
{"learn":[8.232135915],"iteration":10,"passed_time":0.01479837822,"remaining_time":0.1197323329},
{"learn":[7.936645968],"iteration":11,"passed_time":0.01572279524,"remaining_time":0.1153004984},
{"learn":[7.686327869],"iteration":12,"passed_time":0.01663296287,"remaining_time":0.1113129053},
{"learn":[7.453139483],"iteration":13,"passed_time":0.01756868321,"remaining_time":0.1079219111},
{"learn":[7.216574456],"iteration":14,"passed_time":0.01850210881,"remaining_time":0.1048452833},
{"learn":[7.018377399],"iteration":15,"passed_time":0.01940895959,"remaining_time":0.1018970379},
{"learn":[6.823313325],"iteration":16,"passed_time":0.02033090151,"remaining_time":0.09926263677},
{"learn":[6.666946823],"iteration":17,"passed_time":0.02123269185,"remaining_time":0.09672670731},
{"learn":[6.508910347],"iteration":18,"passed_time":0.02214547487,"remaining_time":0.09440965602},
{"learn":[6.386746007],"iteration":19,"passed_time":0.02304817709,"remaining_time":0.09219270837},
{"learn":[6.265973887],"iteration":20,"passed_time":0.02398802595,"remaining_time":0.09024066905},
{"learn":[6.169088554],"iteration":21,"passed_time":0.0251193955,"remaining_time":0.08905967496},
{"learn":[6.063254647],"iteration":22,"passed_time":0.02601855041,"remaining_time":0.0871055818},
{"learn":[5.976012341],"iteration":23,"passed_time":0.02693950027,"remaining_time":0.08530841754},
{"learn":[5.901135024],"iteration":24,"passed_time":0.02784300415,"remaining_time":0.08352901246},
{"learn":[5.835939901],"iteration":25,"passed_time":0.0287430509,"remaining_time":0.08180714486},
{"learn":[5.775227205],"iteration":26,"passed_time":0.02963297676,"remaining_time":0.08011878903},
{"learn":[5.723443194],"iteration":27,"passed_time":0.03054256319,"remaining_time":0.07853801963},
{"learn":[5.680032138],"iteration":28,"passed_time":0.03148749253,"remaining_time":0.07709006791},
{"learn":[5.627248312],"iteration":29,"passed_time":0.03242774221,"remaining_time":0.07566473182},
{"learn":[5.592690321],"iteration":30,"passed_time":0.03333986386,"remaining_time":0.07420808409},
{"learn":[5.544273978],"iteration":31,"passed_time":0.0342516849,"remaining_time":0.07278483041},
{"learn":[5.503344158],"iteration":32,"passed_time":0.03514400571,"remaining_time":0.07135298129},
{"learn":[5.478259921],"iteration":33,"passed_time":0.03608125921,"remaining_time":0.07004009141},
{"learn":[5.442185155],"iteration":34,"passed_time":0.03700719937,"remaining_time":0.06872765598},
{"learn":[5.407844279],"iteration":35,"passed_time":0.03801459758,"remaining_time":0.0675815068},
{"learn":[5.383507306],"iteration":36,"passed_time":0.03909978626,"remaining_time":0.06657531174},
{"learn":[5.362378839],"iteration":37,"passed_time":0.04006878525,"remaining_time":0.06537538646},
{"learn":[5.340630083],"iteration":38,"passed_time":0.04098685919,"remaining_time":0.06410765155},
{"learn":[5.318674311],"iteration":39,"passed_time":0.04189482226,"remaining_time":0.06284223339},
{"learn":[5.302066897],"iteration":40,"passed_time":0.04284937144,"remaining_time":0.06166129061},
{"learn":[5.284928558],"iteration":41,"passed_time":0.04377798713,"remaining_time":0.06045531555},
{"learn":[5.272330995],"iteration":42,"passed_time":0.04472453981,"remaining_time":0.05928601789},
{"learn":[5.261014227],"iteration":43,"passed_time":0.04531236246,"remaining_time":0.05767027949},
{"learn":[5.229469639],"iteration":44,"passed_time":0.04627250317,"remaining_time":0.05655528165},
{"learn":[5.215020572],"iteration":45,"passed_time":0.04719617866,"remaining_time":0.05540420973},
{"learn":[5.193062414],"iteration":46,"passed_time":0.04814646906,"remaining_time":0.05429282681},
{"learn":[5.180484848],"iteration":47,"passed_time":0.04906329041,"remaining_time":0.05315189794},
{"learn":[5.165159502],"iteration":48,"passed_time":0.04999748761,"remaining_time":0.05203820139},
{"learn":[5.141982763],"iteration":49,"passed_time":0.05091574191,"remaining_time":0.05091574191},
{"learn":[5.131085119],"iteration":50,"passed_time":0.05193793063,"remaining_time":0.04990114904},
{"learn":[5.115896901],"iteration":51,"passed_time":0.05288945357,"remaining_time":0.04882103406},
{"learn":[5.102227813],"iteration":52,"passed_time":0.05397239762,"remaining_time":0.04786231487},
{"learn":[5.092694221],"iteration":53,"passed_time":0.0549594238,"remaining_time":0.04681728694},
{"learn":[5.084135611],"iteration":54,"passed_time":0.05596174153,"remaining_time":0.04578687943},
{"learn":[5.067392027],"iteration":55,"passed_time":0.05693934827,"remaining_time":0.04473805936},
{"learn":[5.05548496],"iteration":56,"passed_time":0.0578919334,"remaining_time":0.04367286204},
{"learn":[5.037754059],"iteration":57,"passed_time":0.0588488174,"remaining_time":0.04261466088},
{"learn":[5.018441657],"iteration":58,"passed_time":0.05977478763,"remaining_time":0.04153841174},
{"learn":[5.009952596],"iteration":59,"passed_time":0.06069053676,"remaining_time":0.04046035784},
{"learn":[5.000684433],"iteration":60,"passed_time":0.06163674875,"remaining_time":0.03940710166},
{"learn":[4.982819001],"iteration":61,"passed_time":0.06257818087,"remaining_time":0.03835436892},
{"learn":[4.966552282],"iteration":62,"passed_time":0.0635156448,"remaining_time":0.03730283901},
{"learn":[4.948387795],"iteration":63,"passed_time":0.06445695668,"remaining_time":0.03625703813},
{"learn":[4.933079332],"iteration":64,"passed_time":0.06722237157,"remaining_time":0.03619666162},
{"learn":[4.923067166],"iteration":65,"passed_time":0.06881290836,"remaining_time":0.035449074},
{"learn":[4.91587203],"iteration":66,"passed_time":0.07014835331,"remaining_time":0.03455068148},
{"learn":[4.906625327],"iteration":67,"passed_time":0.07150138454,"remaining_time":0.03364771037},
{"learn":[4.895848666],"iteration":68,"passed_time":0.07293747631,"remaining_time":0.0327690111},
{"learn":[4.886562569],"iteration":69,"passed_time":0.07435832665,"remaining_time":0.03186785428},
{"learn":[4.876525557],"iteration":70,"passed_time":0.07579419877,"remaining_time":0.03095819386},
{"learn":[4.866771122],"iteration":71,"passed_time":0.07723551693,"remaining_time":0.03003603436},
{"learn":[4.860489381],"iteration":72,"passed_time":0.07845210188,"remaining_time":0.02901653083},
{"learn":[4.846895943],"iteration":73,"passed_time":0.0795899548,"remaining_time":0.02796403817},
{"learn":[4.830532583],"iteration":74,"passed_time":0.08109468898,"remaining_time":0.02703156299},
{"learn":[4.818616331],"iteration":75,"passed_time":0.08222596274,"remaining_time":0.0259660935},
{"learn":[4.806132466],"iteration":76,"passed_time":0.08327532752,"remaining_time":0.02487444848},
{"learn":[4.800479202],"iteration":77,"passed_time":0.08428133726,"remaining_time":0.02377165923},
{"learn":[4.797819002],"iteration":78,"passed_time":0.08493796745,"remaining_time":0.02257844704},
{"learn":[4.786614428],"iteration":79,"passed_time":0.08600515821,"remaining_time":0.02150128955},
{"learn":[4.777804595],"iteration":80,"passed_time":0.0870568586,"remaining_time":0.02042074461},
{"learn":[4.767203373],"iteration":81,"passed_time":0.08832117602,"remaining_time":0.01938757522},
{"learn":[4.752577047],"iteration":82,"passed_time":0.08944720976,"remaining_time":0.01832051284},
{"learn":[4.743678884],"iteration":83,"passed_time":0.09065474083,"remaining_time":0.01726756968},
{"learn":[4.737404981],"iteration":84,"passed_time":0.09189772945,"remaining_time":0.01621724637},
{"learn":[4.728022428],"iteration":85,"passed_time":0.09331446209,"remaining_time":0.01519072639},
{"learn":[4.723347156],"iteration":86,"passed_time":0.09446622812,"remaining_time":0.01411564328},
{"learn":[4.717517757],"iteration":87,"passed_time":0.09553889096,"remaining_time":0.01302803059},
{"learn":[4.709503034],"iteration":88,"passed_time":0.0965378718,"remaining_time":0.01193164708},
{"learn":[4.703039995],"iteration":89,"passed_time":0.09746754967,"remaining_time":0.01082972774},
{"learn":[4.696059284],"iteration":90,"passed_time":0.0983762643,"remaining_time":0.009729520645},
{"learn":[4.686066202],"iteration":91,"passed_time":0.09931268609,"remaining_time":0.008635885747},
{"learn":[4.674543063],"iteration":92,"passed_time":0.1002567236,"remaining_time":0.007546205001},
{"learn":[4.671858724],"iteration":93,"passed_time":0.1011910911,"remaining_time":0.006459005817},
{"learn":[4.6586434],"iteration":94,"passed_time":0.1021277133,"remaining_time":0.005375142807},
{"learn":[4.650850795],"iteration":95,"passed_time":0.1030509178,"remaining_time":0.004293788244},
{"learn":[4.647951816],"iteration":96,"passed_time":0.1039465655,"remaining_time":0.003214842233},
{"learn":[4.636294688],"iteration":97,"passed_time":0.1049508473,"remaining_time":0.002141854026},
{"learn":[4.629521481],"iteration":98,"passed_time":0.1065057394,"remaining_time":0.001075815549},
{"learn":[4.625948565],"iteration":99,"passed_time":0.1078661414,"remaining_time":0}
]}